[
    {
        "directory": "C:/dev/c/zmm",
        "file": "src/dep.c",
        "arguments": [
            "clang",
            "-fPIC",
            "-std=c23",
            "-O0",
            "-ggdb3",
            "-Iinclude/",
            "-Iextern/",
            "-c",
            "src/dep.c",
            "-o",
            "build/.obj/src/dep.o"
        ]
    },
    {
        "directory": "C:/dev/c/zmm",
        "file": "src/args.c",
        "arguments": [
            "clang",
            "-fPIC",
            "-std=c23",
            "-O0",
            "-ggdb3",
            "-Iinclude/",
            "-Iextern/",
            "-c",
            "src/args.c",
            "-o",
            "build/.obj/src/args.o"
        ]
    },
    {
        "directory": "C:/dev/c/zmm",
        "file": "src/stb_ds_",
        "arguments": [
            "clang",
            "-fPIC",
            "-std=c23",
            "-O0",
            "-ggdb3",
            "-Iinclude/",
            "-Iextern/",
            "-c",
            "src/slice.c",
            "-o",
            "build/.obj/src/slice.o"
        ]
    },
    {
        "directory": "C:/dev/c/zmm",
        "file": "src/ztime.c",
        "arguments": [
            "clang",
            "-fPIC",
            "-std=c23",
            "-O0",
            "-ggdb3",
            "-Iinclude/",
            "-Iextern/",
            "-c",
            "src/ztime.c",
            "-o",
            "build/.obj/src/ztime.o"
        ]
    },
    {
        "directory": "C:/dev/c/zmm",
        "file": "src/stb_",
        "arguments": [
            "clang",
            "-fPIC",
            "-std=c23",
            "-O0",
            "-ggdb3",
            "-Iinclude/",
            "-Iextern/",
            "-c",
            "src/fs.c",
            "-o",
            "build/.obj/src/fs.o"
        ]
    },
    {
        "directory": "C:/dev/c/zmm",
        "file": "src/stb_ds_src/ar",
        "arguments": [
            "clang",
            "-fPIC",
            "-std=c23",
            "-O0",
            "-ggdb3",
            "-Iinclude/",
            "-Iextern/",
            "-c",
            "src/stb_ds_impl.c",
            "-o",
            "build/.obj/src/stb_ds_impl.o"
        ]
    },
    {
        "directory": "C:/dev/c/zmm",
        "file": "src/cc.c",
        "arguments": [
            "clang",
            "-fPIC",
            "-std=c23",
            "-O0",
            "-ggdb3",
            "-Iinclude/",
            "-Iextern/",
            "-c",
            "src/cc.c",
            "-o",
            "build/.obj/src/cc.o"
        ]
    },
    {
        "directory": "C:/dev/c/zmm",
        "file": "src/cpu.c",
        "arguments": [
            "clang",
            "-fPIC",
            "-std=c23",
            "-O0",
            "-ggdb3",
            "-Iinclude/",
            "-Iextern/",
            "-c",
            "src/cpu.c",
            "-o",
            "build/.obj/src/cpu.o"
        ]
    },
    {
        "directory": "C:/dev/c/zmm",
        "file": "src/sys.c",
        "arguments": [
            "clang",
            "-fPIC",
            "-std=c23",
            "-O0",
            "-ggdb3",
            "-Iinclude/",
            "-Iextern/",
            "-c",
            "src/sys.c",
            "-o",
            "build/.obj/src/sys.o"
        ]
    },
    {
        "directory": "C:/dev/c/zmm",
        "file": "src/arena.c",
        "arguments": [
            "clang",
            "-fPIC",
            "-std=c23",
            "-O0",
            "-ggdb3",
            "-Iinclude/",
            "-Iextern/",
            "-c",
            "src/arena.c",
            "-o",
            "build/.obj/src/arena.o"
        ]
    },
    {
        "directory": "C:/dev/c/zmm",
        "file": "src/builder.c",
        "arguments": [
            "clang",
            "-fPIC",
            "-std=c23",
            "-O0",
            "-ggdb3",
            "-Iinclude/",
            "-Iextern/",
            "-c",
            "src/builder.c",
            "-o",
            "build/.obj/src/builder.o"
        ]
    },
    {
        "directory": "C:/dev/c/zmm",
        "file": "src/slice.c",
        "arguments": [
            "clang",
            "-fPIC",
            "-std=c23",
            "-O0",
            "-ggdb3",
            "-Iinclude/",
            "-Iextern/",
            "-c",
            "src/slice.c",
            "-o",
            "build/.obj/src/slice.o"
        ]
    },
    {
        "directory": "C:/dev/c/zmm",
        "file": "src/fs.c",
        "arguments": [
            "clang",
            "-fPIC",
            "-std=c23",
            "-O0",
            "-ggdb3",
            "-Iinclude/",
            "-Iextern/",
            "-c",
            "src/fs.c",
            "-o",
            "build/.obj/src/fs.o"
        ]
    },
    {
        "directory": "C:/dev/c/zmm",
        "file": "src/stb_ds_impl.c",
        "arguments": [
            "clang",
            "-fPIC",
            "-std=c23",
            "-O0",
            "-ggdb3",
            "-Iinclude/",
            "-Iextern/",
            "-c",
            "src/stb_ds_impl.c",
            "-o",
            "build/.obj/src/stb_ds_impl.o"
        ]
    },
    {
        "directory": "C:/dev/c/zmm",
        "file": "src/path.c",
        "arguments": [
            "clang",
            "-fPIC",
            "-std=c23",
            "-O0",
            "-ggdb3",
            "-Iinclude/",
            "-Iextern/",
            "-c",
            "src/path.c",
            "-o",
            "build/.obj/src/path.o"
        ]
    },
    {
        "directory": "C:/dev/c/zmm",
        "file": "src/print.c",
        "arguments": [
            "clang",
            "-fPIC",
            "-std=c23",
            "-O0",
            "-ggdb3",
            "-Iinclude/",
            "-Iextern/",
            "-c",
            "src/print.c",
            "-o",
            "build/.obj/src/print.o"
        ]
    }
]
